lupulib/__init__.py
lupulib/__main__.py
lupulib/constants.py
lupulib/exceptions.py
lupulib/test.py
lupulib/devices/__init__.py
lupulib/devices/alarm.py
lupulib/devices/binary_sensor.py
lupulib/devices/device.py
lupulib/devices/sensor.py
lupulib/devices/switch.py
lupulib/devices/system.py
lupulib/devices/thermal_switch.py
lupulib/devices/updown_switch.py
lupulib-0.3.94.dist-info/LICENSE
lupulib-0.3.94.dist-info/METADATA
lupulib-0.3.94.dist-info/WHEEL
lupulib-0.3.94.dist-info/entry_points.txt
lupulib-0.3.94.dist-info/top_level.txt
lupulib-0.3.94.dist-info/RECORD
