Metadata-Version: 2.1
Name: lupulib
Version: 0.3.94
Summary: Python-Library to communicate with Lupusec Alarm System
Home-page: https://github.com/piehler73/lupulib
Author: piehler73
Author-email: ahaagner@gmx.de
Project-URL: Bug Tracker, https://github.com/piehler73/lupulib/issues
Classifier: Programming Language :: Python :: 3
Classifier: License :: OSI Approved :: MIT License
Classifier: Operating System :: OS Independent
Requires-Python: >=3.8
License-File: LICENSE
